poridhiframe1/__init__.py
poridhiframe1/api.py
poridhiframe1/middleware.py
poridhiframe1/response.py
poridhiframe1-0.0.2.dist-info/METADATA
poridhiframe1-0.0.2.dist-info/WHEEL
poridhiframe1-0.0.2.dist-info/top_level.txt
poridhiframe1-0.0.2.dist-info/RECORD
